LICENSE
README.md
build_backend.py
build_utils.py
pyproject.toml
requirements.txt
./build_backend.py
./build_utils.py
./csrc/batch_attention.cu
./csrc/batch_attention_customize_config.jinja
./csrc/batch_attention_jit_binding.cu
./csrc/batch_attention_paged_kernel_inst.jinja
./csrc/batch_decode.cu
./csrc/batch_decode_customize_config.jinja
./csrc/batch_decode_jit_binding.cu
./csrc/batch_decode_kernel_inst.jinja
./csrc/batch_decode_mla_binding.cu
./csrc/batch_decode_mla_config.jinja
./csrc/batch_decode_mla_cute_sm80.cu
./csrc/batch_decode_mla_plan.cu
./csrc/batch_decode_mla_run.cu
./csrc/batch_mla_binding.cu
./csrc/batch_mla_config.jinja
./csrc/batch_mla_plan.cu
./csrc/batch_mla_run.cu
./csrc/batch_mla_sm90_binding.cu
./csrc/batch_mla_sm90_plan.cu
./csrc/batch_mla_sm90_run.cu
./csrc/batch_pod.cu
./csrc/batch_pod_customize_config.jinja
./csrc/batch_pod_jit_binding.cu
./csrc/batch_pod_kernel_inst.jinja
./csrc/batch_prefill.cu
./csrc/batch_prefill_customize_config.jinja
./csrc/batch_prefill_fp8_paged_sm90_kernel_inst.jinja
./csrc/batch_prefill_fp8_ragged_sm90_kernel_inst.jinja
./csrc/batch_prefill_fp8_sm90.cu
./csrc/batch_prefill_jit_binding.cu
./csrc/batch_prefill_paged_kernel_inst.jinja
./csrc/batch_prefill_paged_sm90_kernel_inst.jinja
./csrc/batch_prefill_ragged_kernel_inst.jinja
./csrc/batch_prefill_ragged_sm90_kernel_inst.jinja
./csrc/batch_prefill_sm90.cu
./csrc/batch_prefill_sm90_customize_config.jinja
./csrc/batch_prefill_sm90_jit_binding.cu
./csrc/bf16_gemm_cutlass.cu
./csrc/bf16_gemm_cutlass.jinja
./csrc/blackwell_fmha_plan.cu
./csrc/bmm_fp8.cu
./csrc/cascade.cu
./csrc/concat_mla.cu
./csrc/cudnn_sdpa_kernel_launcher.cu
./csrc/cudnn_sdpa_utils.h
./csrc/cutlass_mla.cu
./csrc/dsv3_router_gemm.cu
./csrc/flashinfer_cascade_binding.cu
./csrc/flashinfer_gemm_binding.cu
./csrc/flashinfer_gemm_sm90_binding.cu
./csrc/flashinfer_mamba_binding.cu
./csrc/flashinfer_mla_binding.cu
./csrc/flashinfer_norm_binding.cu
./csrc/flashinfer_page_binding.cu
flashinfer_python.egg-info/PKG-INFO
flashinfer_python.egg-info/SOURCES.txt
flashinfer_python.egg-info/dependency_links.txt
flashinfer_python.egg-info/entry_points.txt
flashinfer_python.egg-info/requires.txt
flashinfer_python.egg-info/top_level.txt
