Metadata-Version: 2.4
Name: flashinfer-python
Version: 0.6.2
Summary: FlashInfer: Kernel Library for LLM Serving
Author: FlashInfer team
License-Expression: Apache-2.0
Project-URL: Homepage, https://github.com/flashinfer-ai/flashinfer
Requires-Python: <4.0,>=3.10
License-File: LICENSE
Requires-Dist: apache-tvm-ffi!=0.1.8,!=0.1.8.post0,<0.2,>=0.1.6
Requires-Dist: click
Requires-Dist: einops
Requires-Dist: ninja
Requires-Dist: numpy
Requires-Dist: nvidia-cudnn-frontend>=1.13.0
Requires-Dist: nvidia-cutlass-dsl>=4.3.4
Requires-Dist: nvidia-ml-py
Requires-Dist: packaging>=24.2
Requires-Dist: requests
Requires-Dist: tabulate
Requires-Dist: torch
Requires-Dist: tqdm
Dynamic: license-file
